{
  "users": [
    {
      "username": "admin",
      "email": "admin@phonestore.com",
      "password": "12345678",
      "fullName": "Admin User",
      "gender": "other",
      "image": "https://example.com/admin_avatar.jpg",
      "isAdmin": true
    },
    {
      "username": "johndoe",
      "email": "john.doe@example.com",
      "password": "johndoepass",
      "fullName": "John Doe",
      "gender": "male",
      "image": "https://example.com/john_avatar.jpg",
      "isAdmin": false
    },
    {
      "username": "janesmith",
      "email": "jane.smith@example.com",
      "password": "janepass",
      "fullName": "Jane Smith",
      "gender": "female",
      "image": "https://example.com/jane_avatar.jpg",
      "isAdmin": false
    }
  ]
}
